multiprocessing.py
setup.py
micropython_multiprocessing.egg-info/PKG-INFO
micropython_multiprocessing.egg-info/SOURCES.txt
micropython_multiprocessing.egg-info/dependency_links.txt
micropython_multiprocessing.egg-info/requires.txt
micropython_multiprocessing.egg-info/top_level.txt