Metadata-Version: 1.0
Name: micropython-multiprocessing
Version: 0.0.2
Summary: multiprocessing module to MicroPython
Home-page: https://github.com/micropython/micropython/issues/405
Author: Paul Sokolovsky
Author-email: micro-python@googlegroups.com
License: MIT
Platform: UNKNOWN
